blockdag/__init__.py
blockdag/blockdag.py
BlockDAG-1.1.3.dist-info/LICENSE
BlockDAG-1.1.3.dist-info/METADATA
BlockDAG-1.1.3.dist-info/WHEEL
BlockDAG-1.1.3.dist-info/top_level.txt
BlockDAG-1.1.3.dist-info/RECORD
