Metadata-Version: 2.2
Name: BlockDAG
Version: 1.1.3
Summary: BlockDAGs for structured signature generation.
Home-page: https://github.com/pritchardn/BlockDAG
Author: Nicholas Pritchard
Author-email: professional@nicpritchard.com
Project-URL: Bug Tracker, https://github.com/pritchardn/BlockDAG/issues
Classifier: Programming Language :: Python :: 3
Classifier: License :: OSI Approved :: MIT License
Classifier: Operating System :: OS Independent
Classifier: Development Status :: 4 - Beta
Classifier: Intended Audience :: Developers
Classifier: Intended Audience :: Science/Research
Classifier: Natural Language :: English
Classifier: Programming Language :: Python :: 3
Requires-Python: >=3.6
License-File: LICENSE
Requires-Dist: np-merklelib>=1.1
